vdna/__init__.py
vdna/distances.py
vdna/vdna_processor.py
vdna/version.py
vdna/networks/__init__.py
vdna/networks/clip.py
vdna/networks/dino_resnet50.py
vdna/networks/dino_vit.py
vdna/networks/feature_extraction_model.py
vdna/networks/inception_pytorch.py
vdna/networks/mugs_vit.py
vdna/networks/random_resnet50.py
vdna/networks/vgg16.py
vdna/utils/im.py
vdna/utils/io.py
vdna/utils/settings.py
vdna/utils/stats.py
vdna/utils/utils.py
vdna/vdnas/__init__.py
vdna/vdnas/vdna_activation_ranges.py
vdna/vdnas/vdna_base.py
vdna/vdnas/vdna_gauss.py
vdna/vdnas/vdna_hist.py
vdna/vdnas/vdna_layer_gauss.py
vdna-0.1.1.dist-info/LICENSE
vdna-0.1.1.dist-info/METADATA
vdna-0.1.1.dist-info/WHEEL
vdna-0.1.1.dist-info/top_level.txt
vdna-0.1.1.dist-info/RECORD
