Metadata-Version: 2.1
Name: vdna
Version: 0.1.1
Summary: A package to compute and compare Visual DNAs, an approach to represent images.
Author-email: Benjamin Ramtoula <benjamin@robots.ox.ac.uk>
Project-URL: Homepage, https://github.com/bramtoula/vdna
Project-URL: Bug Tracker, https://github.com/bramtoula/vdna/issues
Classifier: Programming Language :: Python :: 3
Classifier: License :: OSI Approved :: MIT License
Classifier: Operating System :: OS Independent
Requires-Python: >=3.7
License-File: LICENSE
Requires-Dist: torch
Requires-Dist: torchvision
Requires-Dist: huggingface-hub
Requires-Dist: numpy (>=1.24)
Requires-Dist: opencv-python
Requires-Dist: Pillow
Requires-Dist: scipy
Requires-Dist: tqdm (>=4.64.1)
